gauge_api_steps/__init__.py
gauge_api_steps/api_steps.py
gauge_api_steps/file_util.py
gauge_api_steps/reporting.py
gauge_api_steps/session.py
gauge_api_steps/substitute.py
gauge_api_steps-0.24.dist-info/LICENCE
gauge_api_steps-0.24.dist-info/METADATA
gauge_api_steps-0.24.dist-info/WHEEL
gauge_api_steps-0.24.dist-info/top_level.txt
gauge_api_steps-0.24.dist-info/RECORD
