Metadata-Version: 2.1
Name: gauge-api-steps
Version: 0.24
Summary: Provides steps for a Gauge project, that runs tests against APIs
Home-page: https://github.com/IBM/gauge-api-steps
Author: Tobias Lehmann
Author-email: derdualist1@gmail.com
License: MIT
License-File: LICENCE
Requires-Dist: diff-match-patch==20241021
Requires-Dist: getgauge
Requires-Dist: jsonpath-ng==1.7.0
Requires-Dist: lxml==5.3.0
Requires-Dist: numexpr==2.10.2
Requires-Dist: colorama==0.4.6
